consys4py/__init__.py
consys4py/comm/__init__.py
consys4py/comm/mqtt.py
consys4py/con_sys_api.py
consys4py/constants.py
consys4py/core/default_api_helpers.py
consys4py/datamodels/__init__.py
consys4py/datamodels/api_utils.py
consys4py/datamodels/commands.py
consys4py/datamodels/control_streams.py
consys4py/datamodels/datastreams.py
consys4py/datamodels/encoding.py
consys4py/datamodels/geometry.py
consys4py/datamodels/network_properties.py
consys4py/datamodels/observations.py
consys4py/datamodels/swe_components.py
consys4py/datamodels/system_events_and_history.py
consys4py/endpoints.py
consys4py/part_1/__init__.py
consys4py/part_1/capabilities.py
consys4py/part_1/collections_ep.py
consys4py/part_1/deployments.py
consys4py/part_1/procedures.py
consys4py/part_1/properties.py
consys4py/part_1/sampling_features.py
consys4py/part_1/systems.py
consys4py/part_2/__init__.py
consys4py/part_2/commands.py
consys4py/part_2/control_channels.py
consys4py/part_2/datastreams.py
consys4py/part_2/observations.py
consys4py/part_2/system_events.py
consys4py/part_2/system_history.py
consys4py/querymodel.py
consys4py/request_bodies.py
consys4py/request_wrappers.py
consys4py/sensor_ml/__init__.py
consys4py/sensor_ml/sml.py
consys4py/utilities/__init__.py
consys4py/utilities/model_utils.py
consys4py-0.0.1a8.dist-info/METADATA
consys4py-0.0.1a8.dist-info/WHEEL
consys4py-0.0.1a8.dist-info/RECORD
