Metadata-Version: 2.3
Name: consys4py
Version: 0.0.1a8
Summary: OGC Connected Systems API client for Python
Author: Ian Patterson
Author-email: ian@botts-inc.com
Requires-Python: >=3.10,<4.0
Classifier: Programming Language :: Python :: 3
Classifier: Programming Language :: Python :: 3.10
Classifier: Programming Language :: Python :: 3.11
Classifier: Programming Language :: Python :: 3.12
Classifier: Programming Language :: Python :: 3.13
Requires-Dist: paho-mqtt (>=2.1.0,<3.0.0)
Requires-Dist: pydantic (>=2.7.4,<3.0.0)
Requires-Dist: requests (>=2.26.0,<3.0.0)
